safe_logger
