Metadata-Version: 1.0
Name: safe-logger
Version: 1.5.1
Summary: Safe TimedRotatingFileHandler for concurrent writers
Home-page: https://github.com/cybergrind/safe_logger
Author: cybergrind
Author-email: cybergrind@gmail.com
License: LGPL
Keywords: logging handler concurrent
Platform: UNKNOWN
